trailmet/__init__.py
trailmet/version.py
trailmet/algorithms/__init__.py
trailmet/algorithms/algorithms.py
trailmet/algorithms/binarize/BNNBN.py
trailmet/algorithms/binarize/ReActNet.py
trailmet/algorithms/binarize/__init__.py
trailmet/algorithms/binarize/binarize.py
trailmet/algorithms/binarize/birealnet.py
trailmet/algorithms/binarize/utils.py
trailmet/algorithms/distill/__init__.py
trailmet/algorithms/distill/attention_transfer.py
trailmet/algorithms/distill/distill.py
trailmet/algorithms/distill/factor_transfer.py
trailmet/algorithms/distill/losses.py
trailmet/algorithms/distill/response_kd.py
trailmet/algorithms/distill/rkd.py
trailmet/algorithms/prune/__init__.py
trailmet/algorithms/prune/chip.py
trailmet/algorithms/prune/chipnet.py
trailmet/algorithms/prune/growth_regularisation.py
trailmet/algorithms/prune/network_slimming.py
trailmet/algorithms/prune/pns.py
trailmet/algorithms/prune/prune.py
trailmet/algorithms/prune/utils.py
trailmet/algorithms/prune/pruner/__init__.py
trailmet/algorithms/prune/pruner/l1_pruner.py
trailmet/algorithms/prune/pruner/meta_pruner.py
trailmet/algorithms/prune/pruner/reg_pruner.py
trailmet/algorithms/quantize/__init__.py
trailmet/algorithms/quantize/bitsplit.py
trailmet/algorithms/quantize/brecq.py
trailmet/algorithms/quantize/lapq.py
trailmet/algorithms/quantize/methods.py
trailmet/algorithms/quantize/qmodel.py
trailmet/algorithms/quantize/quantize.py
trailmet/algorithms/quantize/reconstruct.py
trailmet/algorithms/utils/__init__.py
trailmet/datasets/__init__.py
trailmet/datasets/classification/__init__.py
trailmet/datasets/classification/chest.py
trailmet/datasets/classification/cifar.py
trailmet/datasets/classification/dataset.py
trailmet/datasets/classification/imagenet.py
trailmet/datasets/classification/tcga.py
trailmet/models/__init__.py
trailmet/models/base_model.py
trailmet/models/mobilenet.py
trailmet/models/mobilenetv2_bireal.py
trailmet/models/resnet.py
trailmet/models/resnet_bireal.py
trailmet/models/resnet_chip.py
trailmet-0.0.1.1.dist-info/LICENSE
trailmet-0.0.1.1.dist-info/METADATA
trailmet-0.0.1.1.dist-info/WHEEL
trailmet-0.0.1.1.dist-info/top_level.txt
trailmet-0.0.1.1.dist-info/RECORD
