Metadata-Version: 2.1
Name: trailmet
Version: 0.0.1.1
Summary: Transmute AI Model Efficiency Toolkit
Home-page: https://github.com/transmuteAI/trailmet
Author: TrAILMET Contributors
Author-email: transmute.ai@gmail.com
License: MIT License
Keywords: computer vision,image classification,model efficiency
Classifier: Development Status :: 4 - Beta
Classifier: License :: OSI Approved :: Apache Software License
Classifier: Operating System :: OS Independent
Classifier: Programming Language :: Python :: 3
Classifier: Programming Language :: Python :: 3.7
Classifier: Programming Language :: Python :: 3.8
Classifier: Programming Language :: Python :: 3.9
Classifier: Programming Language :: Python :: 3.10
Classifier: Programming Language :: Python :: 3.11
Classifier: Topic :: Scientific/Engineering :: Artificial Intelligence
Requires-Python: >=3.7
License-File: LICENSE
Requires-Dist: codecarbon (==2.2.3)
Requires-Dist: pandas (==2.0.2)
Requires-Dist: tqdm (==4.65.0)
Requires-Dist: timm (==0.9.2)
Requires-Dist: matplotlib (==3.7.1)
Requires-Dist: thop (==0.1.1.post2209072238)
Requires-Dist: scipy (==1.10.1)
Requires-Dist: gdown (==4.7.1)
Requires-Dist: datasets (==2.13.0)
Requires-Dist: scikit-learn (==1.2.2)
Requires-Dist: pytest (==7.3.1)
Requires-Dist: torch-pruning (==1.1.9)
Requires-Dist: wandb (==0.15.4)
Provides-Extra: all
Requires-Dist: codecarbon (==2.2.3) ; extra == 'all'
Requires-Dist: pandas (==2.0.2) ; extra == 'all'
Requires-Dist: tqdm (==4.65.0) ; extra == 'all'
Requires-Dist: timm (==0.9.2) ; extra == 'all'
Requires-Dist: matplotlib (==3.7.1) ; extra == 'all'
Requires-Dist: thop (==0.1.1.post2209072238) ; extra == 'all'
Requires-Dist: scipy (==1.10.1) ; extra == 'all'
Requires-Dist: gdown (==4.7.1) ; extra == 'all'
Requires-Dist: datasets (==2.13.0) ; extra == 'all'
Requires-Dist: scikit-learn (==1.2.2) ; extra == 'all'
Requires-Dist: pytest (==7.3.1) ; extra == 'all'
Requires-Dist: torch-pruning (==1.1.9) ; extra == 'all'
Requires-Dist: wandb (==0.15.4) ; extra == 'all'
